s3utils/__init__.py
s3utils/s3_downloader.py
s3utils/s3_uploader.py
S3_Utils-1.0.0.dist-info/LICENSE
S3_Utils-1.0.0.dist-info/METADATA
S3_Utils-1.0.0.dist-info/WHEEL
S3_Utils-1.0.0.dist-info/top_level.txt
S3_Utils-1.0.0.dist-info/RECORD
