Metadata-Version: 2.1
Name: S3-Utils
Version: 1.0.0
Summary: A S3-Utils package
Home-page: https://github.com/AbhimanyuHK/S3-Utils
Author: Abhimanyu HK
Author-email: manyu1994@hotmail.com
License: UNKNOWN
Platform: UNKNOWN
Classifier: Programming Language :: Python :: 3
Classifier: License :: OSI Approved :: MIT License
Classifier: Operating System :: OS Independent
